mem0_tcvectordb/__init__.py
mem0_tcvectordb/patch.py
mem0_tcvectordb/configs/vector_stores/tcvectordb.py
mem0_tcvectordb/vector_stores/tcvectordb.py
mem0_tcvectordb-0.1.0.dist-info/METADATA
mem0_tcvectordb-0.1.0.dist-info/WHEEL
mem0_tcvectordb-0.1.0.dist-info/licenses/LICENSE
mem0_tcvectordb-0.1.0.dist-info/RECORD
