Metadata-Version: 2.4
Name: mem0-tcvectordb
Version: 0.1.0
Summary: TCVectorDB backend for the mem0 memory framework.
Project-URL: Homepage, https://github.com/alviezhang/mem0-tcvectordb
Project-URL: Source, https://github.com/alviezhang/mem0-tcvectordb
Project-URL: Issues, https://github.com/alviezhang/mem0-tcvectordb/issues
Author: Alvie Zhang
License:                                  Apache License
License-File: LICENSE
Keywords: mem0,memory,tcvectordb,tencent cloud,vector database
Classifier: Development Status :: 4 - Beta
Classifier: Intended Audience :: Developers
Classifier: License :: OSI Approved :: Apache Software License
Classifier: Programming Language :: Python :: 3
Classifier: Programming Language :: Python :: 3.9
Classifier: Programming Language :: Python :: 3.10
Classifier: Programming Language :: Python :: 3.11
Classifier: Programming Language :: Python :: 3.12
Classifier: Programming Language :: Python :: 3.13
Classifier: Programming Language :: Python :: 3.14
Classifier: Topic :: Database
Classifier: Topic :: Scientific/Engineering :: Artificial Intelligence
Requires-Python: <4.0,>=3.9
Requires-Dist: mem0ai<2.0.0,>=1.0.0
Requires-Dist: rank-bm25>=0.2.0
Requires-Dist: tcvectordb>=1.8.0
